tweebo_parser/__init__.py
tweebo_parser/api.py
tweebo_parser_python_api-1.0.4.dist-info/METADATA
tweebo_parser_python_api-1.0.4.dist-info/RECORD
tweebo_parser_python_api-1.0.4.dist-info/WHEEL
tweebo_parser_python_api-1.0.4.dist-info/top_level.txt
