Metadata-Version: 2.1
Name: tweebo-parser-python-api
Version: 1.0.4
Summary: Python 3 API to the TweeboParser
Home-page: https://github.com/apmoore1/tweebo_parser_python_api
Author: Andrew Moore
Author-email: andrew.p.moore94@gmail.com
License: GPLv3
Platform: UNKNOWN
Classifier: Development Status :: 3 - Alpha
Classifier: License :: OSI Approved :: GNU General Public License v3 (GPLv3)
Classifier: Natural Language :: English
Classifier: Programming Language :: Python :: 3.6
Classifier: Topic :: Text Processing
Classifier: Topic :: Text Processing :: Linguistic
Requires-Python: >=3.6
Requires-Dist: requests (>=2.18.4)
